CHANGELOG.md
MANIFEST.in
README.md
VERSION.txt
requirements.txt
setup.py
intrinio/__init__.py
intrinio/client.py
intrinio/endpoints.py
intrinio.egg-info/PKG-INFO
intrinio.egg-info/SOURCES.txt
intrinio.egg-info/dependency_links.txt
intrinio.egg-info/not-zip-safe
intrinio.egg-info/requires.txt
intrinio.egg-info/top_level.txt