Metadata-Version: 1.0
Name: intrinio
Version: 0.2.1
Summary: Intrinio API client
Home-page: https://github.com/nhedlund/intrinio
Author: nhedlund
Author-email: UNKNOWN
License: MIT
Keywords: intrinio,API,data,client,quant,finance
Platform: UNKNOWN
